ati_llamaindex/__init__.py
ati_llamaindex/callbacks.py
ati_llamaindex/instrumentor.py
ati_integrations_llamaindex-0.1.1.dist-info/METADATA
ati_integrations_llamaindex-0.1.1.dist-info/WHEEL
ati_integrations_llamaindex-0.1.1.dist-info/RECORD
