Metadata-Version: 2.4
Name: ati-integrations-llamaindex
Version: 0.1.1
Summary: ATI LlamaIndex integration: retrieval/synthesis callbacks -> ATI spans
Project-URL: Homepage, https://iocane.ai
Project-URL: Repository, https://github.com/iocane-ai/ati-integrations
Requires-Python: >=3.10
Requires-Dist: ati-sdk==0.1.0
Requires-Dist: opentelemetry-api>=1.24.0
Requires-Dist: opentelemetry-sdk>=1.24.0
